{
    "withhtmlpart": {
        "colspanhtml": {
            "preload": [{
                "prescript": "checkhtmltable.template",
                "postscript": "asserhtmltablenumber.template"
            }],
            "postload": ["checkformrowspan.template"]
        },
        "rowspanhtml": {
            "preload": [{
                "prescript": "checkhtmltable.template",
                "postscript": "asserhtmltablenumber.jstemplate"
            },
            {
                "prescript": "checkhtmlformfield.template",
                "postscript": "asserhtmlformfield.jstemplate"
            }],
            "postload":["checkformrowspan.template"]
        },
        "colspanjs" : ["checkjsformcolspan.template"],
        "rowspanjs": ["checkjsformcolspan.template"]
    },
    "withouthtmlpart":{
        "rowspan": ["checkformjsrowspansimplerow.template", "checkformjsrowspandoublerow.template"],
        "colspan": ["checkformjscolspansimplecol.template", "checkformjscolspandoublecol.template"]
    }
}